spraymistf638/__init__.py
spraymistf638/driver.py
spraymistf638-0.1.7.dist-info/LICENSE
spraymistf638-0.1.7.dist-info/WHEEL
spraymistf638-0.1.7.dist-info/METADATA
spraymistf638-0.1.7.dist-info/RECORD
