Metadata-Version: 2.1
Name: spraymistf638
Version: 0.1.7
Summary: 
Home-page: https://github.com/paulokow/Spray-Mist-F638-driver-bluepy
License: Apache-2.0
Author: Pawel Kowalik
Author-email: github-pub@paulonet.eu
Requires-Python: >=3.6.2,<4.0.0
Classifier: Development Status :: 3 - Alpha
Classifier: License :: OSI Approved :: Apache Software License
Classifier: Operating System :: POSIX :: Linux
Classifier: Programming Language :: Python :: 3
Classifier: Programming Language :: Python :: 3.10
Classifier: Programming Language :: Python :: 3.6
Classifier: Programming Language :: Python :: 3.7
Classifier: Programming Language :: Python :: 3.8
Classifier: Programming Language :: Python :: 3.9
Classifier: Topic :: Software Development :: Libraries :: Python Modules
Classifier: Topic :: System :: Hardware :: Hardware Drivers
Requires-Dist: bluepy (>=1.3.0)
Project-URL: Repository, https://github.com/paulokow/Spray-Mist-F638-driver-bluepy
